jorgesomas4/__init__.py
jorgesomas4/soma.py
jorgesomas4-0.1.dist-info/LICENSE
jorgesomas4-0.1.dist-info/METADATA
jorgesomas4-0.1.dist-info/WHEEL
jorgesomas4-0.1.dist-info/top_level.txt
jorgesomas4-0.1.dist-info/RECORD
