Metadata-Version: 2.1
Name: jorgesomas4
Version: 0.1
Summary: Pacote simples de soma
Home-page: https://github.com/JorgeLuis8
Author: Jorge Luis
License: MIT
License-File: LICENSE
